dormer/__init__.py
dormer-0.2.dist-info/LICENSE
dormer-0.2.dist-info/METADATA
dormer-0.2.dist-info/WHEEL
dormer-0.2.dist-info/entry_points.txt
dormer-0.2.dist-info/top_level.txt
dormer-0.2.dist-info/RECORD
