Metadata-Version: 2.1
Name: dormer
Version: 0.2
Summary: Tool for saving/restoring i3 workspace->output mappings
Author-email: Tom Parker-Shemilt <palfrey@tevp.net>
License: AGPL3
Project-URL: Homepage, https://github.com/palfrey/dormer
Classifier: Programming Language :: Python :: 3
Requires-Python: >=3.7
License-File: LICENSE
Requires-Dist: i3ipc
Requires-Dist: pyyaml
Requires-Dist: typing-extensions
